py4wsl/__init__.py
py4wsl/wsl.py
py4wsl-0.0.2.dist-info/licenses/LICENSE
py4wsl-0.0.2.dist-info/METADATA
py4wsl-0.0.2.dist-info/WHEEL
py4wsl-0.0.2.dist-info/top_level.txt
py4wsl-0.0.2.dist-info/RECORD
