Metadata-Version: 2.4
Name: py4wsl
Version: 0.0.2
Summary: A python WSL wrapper
Home-page: https://github.com/ssantosv/py4wsl
Author: Sergio de los Santos
Author-email: Sergio de los Santos <s.delossantos@gmail.com>
License: Copyright (c) 2018 The Python Packaging Authority
Project-URL: Homepage, https://github.com/ssantos/py4wsl
Project-URL: Issues, https://github.com/ssantos/py4wsl/issues
Classifier: Programming Language :: Python :: 3
Classifier: Operating System :: OS Independent
Requires-Python: >=3.7
License-File: LICENSE
Dynamic: author
Dynamic: home-page
Dynamic: license-file
Dynamic: requires-python
